urwid_picker_widgets/__init__.py
urwid_picker_widgets/assisting_modules/__init__.py
urwid_picker_widgets/assisting_modules/modifier_key.py
urwid_picker_widgets/assisting_modules/useful_functions.py
urwid_picker_widgets/widgets/__init__.py
urwid_picker_widgets/widgets/date_picker.py
urwid_picker_widgets/widgets/indicative_listbox.py
urwid_picker_widgets/widgets/integer_picker.py
urwid_picker_widgets/widgets/selectable_row.py
urwid_picker_widgets/widgets/time_picker.py
urwid_picker_widgets-0.4.dist-info/LICENSE
urwid_picker_widgets-0.4.dist-info/METADATA
urwid_picker_widgets-0.4.dist-info/WHEEL
urwid_picker_widgets-0.4.dist-info/top_level.txt
urwid_picker_widgets-0.4.dist-info/RECORD
