Metadata-Version: 2.1
Name: urwid-picker-widgets
Version: 0.4
Summary: Specialized picker widgets for urwid that extend its features.
Home-page: https://github.com/Ezio-Sarthak/urwid_picker_widgets
Author: Sarthak Garg
Author-email: grgsrthk.dev20@gmail.com
License: MIT
Platform: UNKNOWN
Classifier: Programming Language :: Python :: 3
Classifier: License :: OSI Approved :: MIT License
Classifier: Operating System :: Unix
Classifier: Intended Audience :: Developers
Classifier: Environment :: Console
Classifier: Topic :: Software Development :: Widget Sets
Requires-Python: >=3.6
Requires-Dist: urwid
